sleepecg-0.5.9.dist-info/LICENSE
sleepecg-0.5.9.dist-info/WHEEL
sleepecg-0.5.9.dist-info/top_level.txt
sleepecg-0.5.9.dist-info/METADATA
sleepecg-0.5.9.dist-info/RECORD
sleepecg/heartbeats.py
sleepecg/__init__.py
sleepecg/config.yml
sleepecg/utils.py
sleepecg/config.py
sleepecg/_heartbeat_detection.abi3.so
sleepecg/py.typed
sleepecg/_heartbeat_detection.pyi
sleepecg/classification.py
sleepecg/_heartbeat_detection.c
sleepecg/plot.py
sleepecg/feature_extraction.py
sleepecg/classifiers/wrn-gru-mesa-weighted.zip
sleepecg/classifiers/wrn-gru-mesa.zip
sleepecg/classifiers/ws-gru-mesa.zip
sleepecg/io/__init__.py
sleepecg/io/gudb.py
sleepecg/io/ecg_readers.py
sleepecg/io/utils.py
sleepecg/io/sleep_readers.py
sleepecg/io/physionet.py
sleepecg/io/nsrr.py
sleepecg/data/ecg.npz
