Metadata-Version: 2.2
Name: sleepecg
Version: 0.5.9
Summary: A package for sleep stage classification using ECG data
Author-email: Florian Hofer <hofaflo@gmail.com>, Clemens Brunner <clemens.brunner@gmail.com>
License: BSD 3-Clause
Project-URL: homepage, https://github.com/cbrnr/sleepecg
Project-URL: documentation, https://sleepecg.readthedocs.io/en/latest/
Project-URL: repository, https://github.com/cbrnr/sleepecg
Project-URL: changelog, https://github.com/cbrnr/sleepecg/blob/main/CHANGELOG.md
Keywords: sleep,ecg,qrs,peak
Classifier: License :: OSI Approved :: BSD License
Classifier: Operating System :: Microsoft :: Windows
Classifier: Operating System :: POSIX :: Linux
Classifier: Operating System :: MacOS :: MacOS X
Classifier: Programming Language :: Python :: 3
Classifier: Programming Language :: Python :: 3.10
Classifier: Programming Language :: Python :: 3.11
Classifier: Programming Language :: Python :: 3.12
Classifier: Programming Language :: Python :: 3.13
Classifier: Programming Language :: Python :: Implementation :: CPython
Classifier: Typing :: Typed
Requires-Python: >=3.10
License-File: LICENSE
Requires-Dist: numpy>=1.26.0
Requires-Dist: pyyaml>=6.0.0
Requires-Dist: requests>=2.32.3
Requires-Dist: scipy>=1.13.0
Requires-Dist: tqdm>=4.66.0
Provides-Extra: full
Requires-Dist: edfio>=0.4.4; extra == "full"
Requires-Dist: joblib>=1.4.2; extra == "full"
Requires-Dist: matplotlib>=3.9.2; extra == "full"
Requires-Dist: numba>=0.61.0; extra == "full"
Requires-Dist: tensorflow>=2.17.0; python_version < "3.13" and extra == "full"
Requires-Dist: wfdb>=4.2.0; extra == "full"
Provides-Extra: dev
Requires-Dist: sleepecg[doc]; extra == "dev"
Requires-Dist: sleepecg[full]; extra == "dev"
Requires-Dist: mypy>=0.991; extra == "dev"
Requires-Dist: pre-commit>=2.13.0; extra == "dev"
Requires-Dist: pytest>=6.2.0; extra == "dev"
Requires-Dist: pytest-cov>=6.0.0; extra == "dev"
Requires-Dist: ruff>=0.4.0; extra == "dev"
Requires-Dist: setuptools>=72.1.0; extra == "dev"
Provides-Extra: doc
Requires-Dist: mkdocs-material>=9.5.0; extra == "doc"
Requires-Dist: mkdocstrings-python>=1.11.1; extra == "doc"
Provides-Extra: cibw
Requires-Dist: edfio>=0.4.4; extra == "cibw"
Requires-Dist: numba>=0.61.0; platform_machine != "aarch64" and extra == "cibw"
Requires-Dist: wfdb>=4.2.0; extra == "cibw"
